{
  "kind": "coverage_report",
  "version": "1.0",
  "generatedAt": "2026-02-20T07:21:34.003Z",
  "sources": {
    "buildRequest": true,
    "implementationPlan": true
  },
  "requirements": {
    "total": 9,
    "implemented": 9,
    "items": [
      {
        "id": "REQ-41",
        "summary": "Add a PIN code input field to the Careers registration form (frontend/src/pages/Careers.tsx) that accepts manual entry of 6-digit postal codes",
        "status": "implemented",
        "plannedFiles": [
          "frontend/src/pages/Careers.tsx"
        ],
        "matchedFiles": [
          "frontend/src/pages/Careers.tsx"
        ]
      },
      {
        "id": "REQ-42",
        "summary": "Add a PIN code input field to the Vendors registration form (frontend/src/pages/Vendors.tsx) that accepts manual entry of 6-digit postal codes",
        "status": "implemented",
        "plannedFiles": [
          "frontend/src/pages/Vendors.tsx"
        ],
        "matchedFiles": [
          "frontend/src/pages/Vendors.tsx"
        ]
      },
      {
        "id": "REQ-43",
        "summary": "Add a PIN code input field to the Ambulance Services registration form (frontend/src/pages/AmbulanceServices.tsx) that accepts manual entry of 6-digit postal codes",
        "status": "implemented",
        "plannedFiles": [
          "frontend/src/pages/AmbulanceServices.tsx"
        ],
        "matchedFiles": [
          "frontend/src/pages/AmbulanceServices.tsx"
        ]
      },
      {
        "id": "REQ-44",
        "summary": "Add a PIN code input field to the NGO Listing registration form (frontend/src/pages/NgoListing.tsx) that accepts manual entry of 6-digit postal codes",
        "status": "implemented",
        "plannedFiles": [
          "frontend/src/pages/NgoListing.tsx"
        ],
        "matchedFiles": [
          "frontend/src/pages/NgoListing.tsx"
        ]
      },
      {
        "id": "REQ-45",
        "summary": "Implement auto-fill functionality that automatically populates the city and state fields when a valid PIN code is entered in the Careers registration form",
        "status": "implemented",
        "plannedFiles": [
          "frontend/src/pages/Careers.tsx"
        ],
        "matchedFiles": [
          "frontend/src/pages/Careers.tsx"
        ]
      },
      {
        "id": "REQ-46",
        "summary": "Implement auto-fill functionality that automatically populates the city and state fields when a valid PIN code is entered in the Vendors registration form",
        "status": "implemented",
        "plannedFiles": [
          "frontend/src/pages/Vendors.tsx"
        ],
        "matchedFiles": [
          "frontend/src/pages/Vendors.tsx"
        ]
      },
      {
        "id": "REQ-47",
        "summary": "Implement auto-fill functionality that automatically populates the city and state fields when a valid PIN code is entered in the Ambulance Services registration form",
        "status": "implemented",
        "plannedFiles": [
          "frontend/src/pages/AmbulanceServices.tsx"
        ],
        "matchedFiles": [
          "frontend/src/pages/AmbulanceServices.tsx"
        ]
      },
      {
        "id": "REQ-48",
        "summary": "Implement auto-fill functionality that automatically populates the city and state fields when a valid PIN code is entered in the NGO Listing registration form",
        "status": "implemented",
        "plannedFiles": [
          "frontend/src/pages/NgoListing.tsx"
        ],
        "matchedFiles": [
          "frontend/src/pages/NgoListing.tsx"
        ]
      },
      {
        "id": "REQ-49",
        "summary": "Create a PIN code lookup utility or API integration that maps Indian postal codes to their corresponding city and state information for the auto-fill functionality",
        "status": "implemented",
        "plannedFiles": [
          "frontend/src/utils/pinCodeLookup.ts"
        ],
        "matchedFiles": [
          "frontend/src/utils/pinCodeLookup.ts"
        ]
      }
    ]
  },
  "changedFiles": [
    "backend/http-outcalls/outcall.mo",
    "build-request.json",
    "caffeine.lock.json",
    "feature_evidence.json",
    "frontend-file-summaries.txt",
    "frontend-implementation-plan.json",
    "frontend/src/pages/AmbulanceServices.tsx",
    "frontend/src/pages/Careers.tsx",
    "frontend/src/pages/NgoListing.tsx",
    "frontend/src/pages/Vendors.tsx",
    "frontend/src/utils/pinCodeLookup.ts",
    "project_state.json",
    "scratch/component-selection.json",
    "spec.md",
    "spec_vs_diff_report.json"
  ]
}